Newmode/__init__.py
newmode-0.1.6.dist-info/LICENSE
newmode-0.1.6.dist-info/METADATA
newmode-0.1.6.dist-info/WHEEL
newmode-0.1.6.dist-info/top_level.txt
newmode-0.1.6.dist-info/RECORD
