Metadata-Version: 2.1
Name: newmode
Version: 0.1.6
Summary: New/Mode API Wrapper
Home-page: https://github.com/NewMode/python
Author: New/Mode
Author-email: info@newmode.net
License: UNKNOWN
Platform: UNKNOWN
Classifier: Programming Language :: Python :: 3
Classifier: License :: OSI Approved :: MIT License
Classifier: Operating System :: OS Independent
Requires-Python: >=3.6
